dotsinspace_debugger/__init__.py
dotsinspace_debugger-1.0.6.dist-info/METADATA
dotsinspace_debugger-1.0.6.dist-info/WHEEL
dotsinspace_debugger-1.0.6.dist-info/top_level.txt
dotsinspace_debugger-1.0.6.dist-info/RECORD
