Metadata-Version: 2.1
Name: dotsinspace-debugger
Version: 1.0.6
Summary: Debugger for colorful logging.
Home-page: https://github.com/dotsinspace/Debugger
Author: dotsinspace
Author-email: dotsinspace <dotsinspace@gmail.com>
Maintainer: dotsinspace
Maintainer-email: dotsinspace <dotsinspace@gmail.com>
License: MIT License
Project-URL: Homepage, https://github.com/dotsinspace/Debugger
Project-URL: Bug Reports, https://github.com/dotsinspace/Debugger/issues
Project-URL: Funding, https://donate.pypi.org
Project-URL: Say Thanks!, http://saythanks.io/dotsinspace
Project-URL: Source, https://github.com/dotsinspace/Debugger
Keywords: utility,debugger
Classifier: Programming Language :: Python :: 3
Classifier: Programming Language :: Python :: 3.8
Classifier: Programming Language :: Python :: 3.9
Requires-Python: >=3.8
Requires-Dist: ujson
Requires-Dist: aiofiles
Requires-Dist: sentry-sdk
Requires-Dist: colorama
